{
    "info": {
        "地址": "臺北市北投區稻香路３２１號１樓",
        "所屬工業區": "非屬工業區類",
        "管制編號": "A4405671",
        "行業別": "居住型照顧服務業(居住型老人照顧服務業)",
        "列管類別": "廢棄物;",
        "最新資料匯入日期": "2017\/12\/01",
        "更新頻率": "每日",
        "longitude": "121.486539823189",
        "latitude": "25.1429138269581",
        "name": "台北市私立聖心老人養護所"
    },
    "reports": {
        "AIR": [],
        "WAT": [],
        "WAS": [],
        "TOX": [],
        "METAL": [],
        "GREENHOUSE": [],
        "PENALTY": []
    }
}